stldecompose/__init__.py
stldecompose/__version__.py
stldecompose/forecast_funcs.py
stldecompose/stl.py
stldecompose-mod/__init__.py
stldecompose-mod/__version__.py
stldecompose-mod/forecast_funcs.py
stldecompose-mod/stl.py
stldecompose_mod/__init__.py
stldecompose_mod/__version__.py
stldecompose_mod/forecast_funcs.py
stldecompose_mod/stl.py
stldecomposemod/__init__.py
stldecomposemod/__version__.py
stldecomposemod/forecast_funcs.py
stldecomposemod/stl.py
stldecomposemod-0.0.3.dist-info/DESCRIPTION.rst
stldecomposemod-0.0.3.dist-info/METADATA
stldecomposemod-0.0.3.dist-info/RECORD
stldecomposemod-0.0.3.dist-info/WHEEL
stldecomposemod-0.0.3.dist-info/metadata.json
stldecomposemod-0.0.3.dist-info/top_level.txt
