Metadata-Version: 2.0
Name: stldecomposemod
Version: 0.0.3
Summary: A Python implementation of seasonal trend with Loess (STL) time series decomposition MODIFIED
Home-page: UNKNOWN
Author: Goh Kun Shun
Author-email: gohkunshun@airasia.com
License: MIT
Platform: UNKNOWN
Classifier: License :: OSI Approved :: MIT License
Classifier: Programming Language :: Python
Classifier: Programming Language :: Python :: 2.7
Classifier: Programming Language :: Python :: 3
Classifier: Programming Language :: Python :: 3.3
Classifier: Programming Language :: Python :: 3.4
Classifier: Programming Language :: Python :: 3.5
Classifier: Programming Language :: Python :: 3.6
Classifier: Programming Language :: Python :: Implementation :: CPython
Classifier: Programming Language :: Python :: Implementation :: PyPy
Classifier: Development Status :: 3 - Alpha
Classifier: Topic :: Scientific/Engineering
Requires-Dist: pandas
Requires-Dist: numpy
Requires-Dist: statsmodels
Requires-Dist: matplotlib
